{
	"labels":[
		{
			"labelName":"cdField1",
			"labelDispName": "field1"
		},
		{
			"labelName":"cdField2",
			"labelDispName": "field2"
		},
		{
			"labelName":"cdField3",
			"labelDispName": "field3"
		},
		{
			"labelName":"cdField4",
			"labelDispName": "field4"
		},
		{
			"labelName":"cdField5",
			"labelDispName": "field5"
		},
		{
			"labelName":"cdField6",
			"labelDispName": "field6"
		},
		{
			"labelName":"cdField7",
			"labelDispName": "field7"
		},
		{
			"labelName":"cdField8",
			"labelDispName": "field8"
		},
		{
			"labelName":"cdField9",
			"labelDispName": "field9"
		},

		{
			"labelName":"cdField10",
			"labelDispName": "field10"
		}


	]


}